insolation/__init__.py
insolation/atmosf.py
insolation/constant.py
insolation/insolf.py
insolation/shadows.py
insolation-0.1.9.dist-info/LICENSE
insolation-0.1.9.dist-info/METADATA
insolation-0.1.9.dist-info/WHEEL
insolation-0.1.9.dist-info/top_level.txt
insolation-0.1.9.dist-info/RECORD
