Metadata-Version: 2.1
Name: insolation
Version: 0.1.9
Summary: Functions to compute insolation over complex terrain
Author-email: "Javier G. Corripio" <jgc@meteoexploration.com>
Project-URL: Homepage, https://www.meteoexploration.com/insol/python/index.html
Project-URL: Bug Tracker, https://github.com/jgcmeteo/insolation/issues
Classifier: Development Status :: 4 - Beta
Classifier: Intended Audience :: Science/Research
Classifier: Programming Language :: Python :: 3
Classifier: License :: OSI Approved :: MIT License
Classifier: Operating System :: OS Independent
Requires-Python: >=3.7
License-File: LICENSE
